{"_ts":[1543644591],"_r":{"breakdown":{"html":{"bytes":[10425],"requests":[1]},"js":{"bytes":[20051],"requests":[2]},"css":{"bytes":[60295],"requests":[2]},"image":{"bytes":[6361],"requests":[7]},"flash":{"bytes":[0],"requests":[0]},"font":{"bytes":[186184],"requests":[6]},"video":{"bytes":[0],"requests":[0]},"other":{"bytes":[585],"requests":[1]}},"date":[1543644591],"domElements":[216],"domInteractive":[937],"firstPaint":[929.0999999976],"fullyLoaded":[2028],"id":["181201_2K_8b5f81b64e0a79d28045a4bbc7554c31"],"loadTime":[1541],"render":[900],"SpeedIndex":[917],"TTFB":[659],"videoFrames":[[{"_i":"ms_000000.jpg","_t":0,"_vc":0},{"_i":"ms_000900.jpg","_t":900,"_vc":99},{"_i":"ms_001100.jpg","_t":1100,"_vc":95},{"_i":"ms_001300.jpg","_t":1300,"_vc":95},{"_i":"ms_001400.jpg","_t":1400,"_vc":100},{"_i":"ms_001500.jpg","_t":1500,"_vc":100}]],"visualComplete":[1400],"lighthouse":[57],"pagespeed":[null]}}